Make.mm
setup.py
uploadPackage.sh
plotlib/Line.py
plotlib/Make.mm
plotlib/NcPlottable.py
plotlib/NcPlottableSet.py
plotlib/TextPlottable.py
plotlib/VnfPlot.py
plotlib/__init__.py
plotlib/mlab.py
plotlib/trajectoryPlot.py
plotlib/triangulate.py
plotlib/types.py
plotlib.egg-info/PKG-INFO
plotlib.egg-info/SOURCES.txt
plotlib.egg-info/dependency_links.txt
plotlib.egg-info/top_level.txt