Metadata-Version: 1.0
Name: plotlib
Version: 0.3
Summary: library to plot data objects of vnf and danse products
Home-page: UNKNOWN
Author: J. Brandon Keith
Author-email: jbrkeith@gmail.edu
License: BSD
Keywords: plot vnf
Platform: UNKNOWN
Classifier: Development Status :: 5 - Production/Stable
Classifier: Environment :: Console
Classifier: Intended Audience :: Science/Research
Classifier: Operating System :: MacOS
Classifier: Operating System :: Microsoft :: Windows
Classifier: Operating System :: POSIX
Classifier: Programming Language :: Python :: 2.6
Classifier: Topic :: Scientific/Engineering :: Physics
